repensedb/aws/secrets_manager.py
repensedb/connections/base.py
repensedb/connections/factory.py
repensedb/connections/firebase.py
repensedb/connections/mysql.py
repensedb/connections/postgres.py
repensedb/connections/redis.py
repensedb/connections/sqlite.py
repensedb/database/firebase/auth.py
repensedb/database/firebase/manager.py
repensedb/database/mysql/manager.py
repensedb/database/postgres/manager.py
repensedb/database/redis/manager.py
repensedb/database/sqlite/manager.py
repensedb/utils/logs.py
repensedb/utils/password.py
repensedb/utils/text.py
repensedb/utils/user_info.py
repensedb-1.1.15.dist-info/LICENSE
repensedb-1.1.15.dist-info/METADATA
repensedb-1.1.15.dist-info/WHEEL
repensedb-1.1.15.dist-info/RECORD
