Metadata-Version: 2.1
Name: repensedb
Version: 1.1.15
Summary: A powerful and flexible database manipulation library that provides a unified interface for multiple database systems.
Author: Samuel Alessandro Baptista
Author-email: samuel.baptista@repense.ai
Requires-Python: >=3.10,<4.0
Classifier: Programming Language :: Python :: 3
Classifier: Programming Language :: Python :: 3.10
Classifier: Programming Language :: Python :: 3.11
Classifier: Programming Language :: Python :: 3.12
Requires-Dist: boto3 (>=1.35.14,<2.0.0)
Requires-Dist: firebase-admin (>=6.5.0,<7.0.0)
Requires-Dist: mysql-connector-python (>=9.0.0,<10.0.0)
Requires-Dist: pandas (>=2.2.2,<3.0.0)
Requires-Dist: psycopg2-binary (>=2.9.10,<3.0.0)
Requires-Dist: pytest (>=8.3.3,<9.0.0)
Requires-Dist: redis (>=5.2.0,<6.0.0)
Requires-Dist: setuptools (>=75.2.0,<76.0.0)
